raven/io/dataframe/__init__.py
raven/io/dataframe/csvfiles.py
raven/io/dataframe/dataframes.py
raven/struct/dataframe/__init__.py
raven/struct/dataframe/_columnutils.py
raven/struct/dataframe/_dataframeutils.py
raven/struct/dataframe/binarycolumn.py
raven/struct/dataframe/booleancolumn.py
raven/struct/dataframe/bytecolumn.py
raven/struct/dataframe/charcolumn.py
raven/struct/dataframe/column.py
raven/struct/dataframe/core.py
raven/struct/dataframe/doublecolumn.py
raven/struct/dataframe/floatcolumn.py
raven/struct/dataframe/intcolumn.py
raven/struct/dataframe/longcolumn.py
raven/struct/dataframe/shortcolumn.py
raven/struct/dataframe/stringcolumn.py
raven_pydf-1.1.4.dist-info/LICENSE
raven_pydf-1.1.4.dist-info/METADATA
raven_pydf-1.1.4.dist-info/WHEEL
raven_pydf-1.1.4.dist-info/top_level.txt
raven_pydf-1.1.4.dist-info/RECORD
