Metadata-Version: 2.1
Name: raven-pydf
Version: 1.1.4
Summary: An implementation of the DataFrame specification in Python
Home-page: https://github.com/raven-computing/pydf
Author: Phil Gaiser
Author-email: phil.gaiser@raven-computing.com
License: Apache Software License
Platform: UNKNOWN
Classifier: Programming Language :: Python :: 3
Classifier: License :: OSI Approved :: Apache Software License
Classifier: Operating System :: OS Independent
Requires-Python: >=3.7
Requires-Dist: numpy (>=1.19.0)
